portfolio_analyzer/__init__.py
portfolio_analyzer/analyzer.py
portfolio_analyzer/cli.py
portfolio_analyzer/csv_parser.py
portfolio_analyzer/models.py
portfolio_analyzer/utils.py
portfolio_analyzer-0.1.1.dist-info/entry_points.txt
portfolio_analyzer-0.1.1.dist-info/WHEEL
portfolio_analyzer-0.1.1.dist-info/METADATA
portfolio_analyzer-0.1.1.dist-info/RECORD
